odoo/addons/stock_barcodes_gs1/README.rst
odoo/addons/stock_barcodes_gs1/__init__.py
odoo/addons/stock_barcodes_gs1/__manifest__.py
odoo/addons/stock_barcodes_gs1/i18n/ca.po
odoo/addons/stock_barcodes_gs1/i18n/es.po
odoo/addons/stock_barcodes_gs1/i18n/stock_barcodes_gs1.pot
odoo/addons/stock_barcodes_gs1/readme/CONTRIBUTORS.rst
odoo/addons/stock_barcodes_gs1/readme/DESCRIPTION.rst
odoo/addons/stock_barcodes_gs1/readme/USAGE.rst
odoo/addons/stock_barcodes_gs1/static/description/icon.png
odoo/addons/stock_barcodes_gs1/static/description/index.html
odoo/addons/stock_barcodes_gs1/tests/__init__.py
odoo/addons/stock_barcodes_gs1/tests/test_stock_barcodes_gs1.py
odoo/addons/stock_barcodes_gs1/tests/test_stock_barcodes_new_lot_gs1.py
odoo/addons/stock_barcodes_gs1/wizard/__init__.py
odoo/addons/stock_barcodes_gs1/wizard/stock_barcodes_read.py
odoo/addons/stock_barcodes_gs1/wizard/stock_production_lot.py
odoo14_addon_stock_barcodes_gs1-14.0.2.0.1.dist-info/METADATA
odoo14_addon_stock_barcodes_gs1-14.0.2.0.1.dist-info/WHEEL
odoo14_addon_stock_barcodes_gs1-14.0.2.0.1.dist-info/top_level.txt
odoo14_addon_stock_barcodes_gs1-14.0.2.0.1.dist-info/RECORD
